{"title": "Quake drill: drop, cover and hold on", "filename": "1993-04-23_QuakeDrillDropCoverAndHoldOn.json", "url": "http://infoweb.newsbank.com/resources/doc/nb/news/0EB536626CEA73F8?p=WORLDNEWS", "date": "1993-04-23", "page": "D3", "section": "South", "author": "Unknown", "text": "QUAKE DRILL: DROP, COVER AND HOLD ON: CHANTEL ALBERT, THIRD-GRADER AT EVERGREEN HEIGHTS ELEMENTARY SCHOOL IN AUBURN,\"DROPS, COVERS, AND HOLDS\" AS HER CLASSMATES OBSERVE DURING AN EARTHQUAKE-AWARENESS WEEK PRESENTATION BY THE AUBURN FIRE DEPARTMENT. FIRE PERSONNEL  ARE BRINGING DISASTER-PREPAREDNESS EDUCATION TO ELEMENTARY SCHOOLS THROUGHOUT THE CITYCaption:  PHOTOCHIEN-CHI CHANG / SEATTLE TIMES: QUAKE DRILL: DROP, COVER AND HOLD ON", "edition": "Final"}