{"title": "No injuries in 2.9 quake", "filename": "1996-12-16_NoInjuriesIn29Quake.json", "url": "http://infoweb.newsbank.com/resources/doc/nb/news/0EB538A0C8564D33?p=WORLDNEWS", "date": "1996-12-16", "page": "B2", "section": "Local News", "author": "Seattle Times Staffseattle Times News Services", "text": "SEATTLE - A small earthquake with a magnitude of 2.9 occurred yesterday 26 miles southwest of Mount Olympus on the Olympic Peninsula, the University of Washington Seismology Lab reported.    The quake occurred at 12:34 a.m. It was centered 34 miles northwest of Aberdeen, and 20 miles below the Earth's surface, the agency said. No damage or injuries were reported.", "edition": "Final"}