{"title": "Earthquake danger - one minor shake could bury $1 billion worth of stadiums", "filename": "1997-06-23_EarthquakeDanger-OneMinorShakeCouldBury$1BillionWorthOfStadiums.json", "url": "http://infoweb.newsbank.com/resources/doc/nb/news/0EB538DB2F4F9A7A?p=WORLDNEWS", "date": "1997-06-23", "page": "B5", "section": "Editorial", "author": "Unknown", "text": "While viewing the textbook photo of the Kingdome on page B7, ( June 15), I felt as though I was viewing Atlantis.     One minor shake, slide or tremor could put $1 billion worth of sports stadiums under at least 20 feet of water with all insurance bets off because it was caused by an act of God! Kaye Pethe Lake Forest Par", "edition": "Final"}